FRS1/Image_Dataset_Generator.py
FRS1/__init__.py
FRS1/face_recognizeronly.py
FRS1/haarcascade_frontalface_default.xml
FRS1/nn4.small2.v1.h5
FRS1/shape_predictor_68_face_landmarks.dat
FRS1-0.0.1.dist-info/AUTHORS.rst
FRS1-0.0.1.dist-info/LICENSE
FRS1-0.0.1.dist-info/METADATA
FRS1-0.0.1.dist-info/WHEEL
FRS1-0.0.1.dist-info/top_level.txt
FRS1-0.0.1.dist-info/RECORD
